anymusic/__init__.py
anymusic/basic.py
anymusic/scale.py
anymusic/timbre.py
anymusic/type.py
anymusic/wave.py
anymusic-0.0.1.dist-info/WHEEL
anymusic-0.0.1.dist-info/METADATA
anymusic-0.0.1.dist-info/RECORD
